{"_path":"/","_dir":"","_draft":false,"_partial":false,"_locale":"","title":"","description":"","body":{"type":"root","children":[{"type":"element","tag":"h1","props":{"id":""},"children":[]},{"type":"element","tag":"h1","props":{"id":"weinnovatedesign"},"children":[{"type":"text","value":"WeInnovate.Design"}]},{"type":"element","tag":"p","props":{},"children":[{"type":"text","value":"Web Technology Design, Dev & Consultancy"}]},{"type":"element","tag":"h2","props":{"id":"web-technology-expert"},"children":[{"type":"text","value":"Web Technology Expert"}]},{"type":"element","tag":"p","props":{},"children":[{"type":"text","value":"Helping small to medium businesses optimise their customer engagment and experience using the latest web technologies and best practices."}]},{"type":"element","tag":"h3","props":{"id":"web-design-development-and-consultancy-services-based-in-adelaide"},"children":[{"type":"text","value":"Web Design, Development and Consultancy services based in Adelaide"}]},{"type":"element","tag":"ul","props":{},"children":[{"type":"element","tag":"li","props":{},"children":[{"type":"text","value":"Website Design and Development"}]},{"type":"element","tag":"li","props":{},"children":[{"type":"text","value":"MarTech Onboarding, Implementation and Integration"}]},{"type":"element","tag":"li","props":{},"children":[{"type":"text","value":"Saas Product Strategy - UI/UX, Onboarding, Research & Content Marketing"}]},{"type":"element","tag":"li","props":{},"children":[{"type":"text","value":"Google Adwords Management, Optimisation and Reporting"}]},{"type":"element","tag":"li","props":{},"children":[{"type":"text","value":"Customised SEO service"}]}]},{"type":"element","tag":"p","props":{},"children":[{"type":"text","value":"Email at contact[at]weinnovate.design"}]}],"toc":{"title":"","searchDepth":2,"depth":2,"links":[{"id":"web-technology-expert","depth":2,"text":"Web Technology Expert","children":[{"id":"web-design-development-and-consultancy-services-based-in-adelaide","depth":3,"text":"Web Design, Development and Consultancy services based in Adelaide"}]}]}},"_type":"markdown","_id":"content:index.md","_source":"content","_file":"index.md","_extension":"md"}